README.md
setup.py
GlodonLibrary/__init__.py
GlodonLibrary/version.py
GlodonLibrary/keywords/GTFLibrary.py
GlodonLibrary/keywords/__init__.py
GlodonLibrary/keywords/_fileRead.py
GlodonLibrary/keywords/_httpreq.py
GlodonLibrary/keywords/_locksetting.py
GlodonLibrary/keywords/_mysql.py
GlodonLibrary/keywords/_redisOpr.py
GlodonLibrary/keywords/_sqlite.py
GlodonLibrary/keywords/_utils.py
GlodonLibrary/keywords/_win_func.py
glodonLib.egg-info/PKG-INFO
glodonLib.egg-info/SOURCES.txt
glodonLib.egg-info/dependency_links.txt
glodonLib.egg-info/requires.txt
glodonLib.egg-info/top_level.txt