Metadata-Version: 1.0
Name: glodonLib
Version: 0.4.0
Summary: common functions
Home-page: https://github.com/upengfei/glodonLib
Author: upengfei
Author-email: yu.pf@163.com
License: MIT Licence
Keywords: pip,glodonLib
Platform: win32
